[
 {
  "id": "1644228165691",
  "value": "Literal",
  "placeholder": "My beautiful title",
  "type": "Textbox",
  "label": "title",
  "property": "http://schema.org/title",
  "disambiguate": "True",
  "prepend": "A textbox with a literal value, flagged as main title of the record (mandatory)",
  "browse": "False",
  "searchWikidata": "False",
  "searchGeonames": "False",
  "disabled": "False",
  "class": "col-md-11",
  "cache_autocomplete": "off"
 },
 {
  "id": "1644228232251",
  "prepend": "A text area. After filling in the field, press return to extract named entities (people names, places, organisations). ",
  "label": "Description",
  "placeholder": "I was born in Tokyo. When I was 13 I moved to Rome.",
  "type": "Textarea",
  "property": "http://schema.org/description",
  "disambiguate": "False",
  "browse": "False",
  "value": "Literal",
  "searchWikidata": "False",
  "searchGeonames": "False",
  "disabled": "False",
  "class": "col-md-11",
  "cache_autocomplete": "off"
 },
 {
  "id": "1644228345066",
  "browse": "True",
  "property": "http://schema.org/gender",
  "type": "Dropdown",
  "prepend": "A dropdown. Select only one value from the controlled vocabulary of terms. Show this field in the Explore page",
  "label": "Gender",
  "values": {
   "http://example.org/female": "female",
   "http://example.org/male": "male",
   "http://example.org/other": "other"
  },
  "value": "URI",
  "disambiguate": "False",
  "searchWikidata": "False",
  "searchGeonames": "False",
  "disabled": "False",
  "class": "col-md-11",
  "cache_autocomplete": "off"
 },
 {
  "id": "1644228758707",
  "label": "Affiliation",
  "prepend": "A checkbox. Select multiple one values from the controlled vocabulary of terms. Show this field in the Explore page",
  "browse": "True",
  "property": "http://schema.org/memberOf",
  "values": {
   "http://example.org/unibo": "University of Bologna",
   "http://example.org/dharc": "Digital Humanities Research Centre",
   "http://example.org/polifonia": "Polifonia H2020"
  },
  "type": "Checkbox",
  "value": "URI",
  "disambiguate": "False",
  "searchWikidata": "False",
  "searchGeonames": "False",
  "disabled": "False",
  "class": "col-md-11",
  "cache_autocomplete": "off"
 },
 {
  "id": "1644229044498",
  "label": "Friend of",
  "property": "http://schema.org/knows",
  "placeholder": "e.g. Federico Fellini",
  "prepend": "A text box with an entity value. Searches in Wikidata for matches while you type, press return to accept suggestions. You can search and select multiple values.",
  "type": "Textbox",
  "value": "URI",
  "disambiguate": "False",
  "browse": "False",
  "searchWikidata": "True",
  "searchGeonames": "False",
  "disabled": "False",
  "class": "col-md-11",
  "cache_autocomplete": "off"
 },
 {
  "id": "1644229155148",
  "prepend": "A text box with a location value. Searches in Geonames for matches while you type, press return to accept suggestions. You can search and select multiple values.",
  "type": "Textbox",
  "placeholder": "Bologna",
  "label": "Birth place",
  "property": "http://schema.org/birthPlace",
  "value": "Place",
  "disambiguate": "False",
  "browse": "False",
  "searchWikidata": "False",
  "searchGeonames": "True",
  "disabled": "False",
  "class": "col-md-11",
  "cache_autocomplete": "off"
 }
]